cmissh/__init__.py
cmissh/atompub/__init__.py
cmissh/atompub/binding.py
cmissh/browser/__init__.py
cmissh/browser/binding.py
cmissh/cli.py
cmissh/cmis_services.py
cmissh/domain.py
cmissh/exceptions.py
cmissh/messages.py
cmissh/model.py
cmissh/shell.py
cmissh/tck/README.md
cmissh/tck/__init__.py
cmissh/tck/cli.py
cmissh/tck/runner.py
cmissh/tck/suite.py
cmissh/tck/suites/__init__.py
cmissh/tck/suites/basic.py
cmissh/tck/suites/documents.py
cmissh/tck/suites/folders.py
cmissh/tck/suites/navigation.py
cmissh/tck/suites/properties.py
cmissh/tck/suites/repository.py
cmissh/tck/suites/versioning.py
cmissh/util.py
cmissh-2026.1.0.dist-info/WHEEL
cmissh-2026.1.0.dist-info/entry_points.txt
cmissh-2026.1.0.dist-info/METADATA
cmissh-2026.1.0.dist-info/RECORD
