Metadata-Version: 2.3
Name: cmissh
Version: 2026.1.0
Summary: CMIS Python client library and command-line shell
Keywords: cmis,content-management,ecm,cli
Author: Apache Chemistry Project
Author-email: Apache Chemistry Project <dev@chemistry.apache.org>
License: Apache-2.0
Classifier: Development Status :: 3 - Alpha
Classifier: Intended Audience :: Developers
Classifier: License :: OSI Approved :: Apache Software License
Classifier: Operating System :: OS Independent
Classifier: Programming Language :: Python :: 3
Classifier: Programming Language :: Python :: 3.10
Classifier: Programming Language :: Python :: 3.11
Classifier: Programming Language :: Python :: 3.12
Classifier: Programming Language :: Python :: 3.13
Classifier: Programming Language :: Python :: 3.14
Classifier: Topic :: Software Development :: Libraries
Classifier: Topic :: System :: Systems Administration
Requires-Dist: iso8601>=2.1.0
Requires-Dist: pytest>=8.4.2
Requires-Dist: requests>=2.31.0
Requires-Dist: requests-toolbelt>=1.0.0
Requires-Python: >=3.10
Project-URL: Documentation, https://github.com/your-repo/cmissh
Project-URL: Homepage, https://github.com/your-repo/cmissh
Project-URL: Repository, https://github.com/your-repo/cmissh
